magic_prompt/__init__.py
magic_prompt/__main__.py
magic_prompt/app.py
magic_prompt/cli.py
magic_prompt/config.py
magic_prompt/enricher.py
magic_prompt/groq_client.py
magic_prompt/keyboard.py
magic_prompt/raycast.py
magic_prompt/retriever.py
magic_prompt/scanner.py
magic_prompt/settings.py
magic_prompt/workspace_screen.py
magic_prompt/workspaces.py
magic_prompt/modes/__init__.py
magic_prompt/modes/elaboration.py
magic_prompt/modes/pseudocode.py
ai_magic_prompt-0.5.1.dist-info/METADATA
ai_magic_prompt-0.5.1.dist-info/WHEEL
ai_magic_prompt-0.5.1.dist-info/entry_points.txt
ai_magic_prompt-0.5.1.dist-info/licenses/LICENSE
ai_magic_prompt-0.5.1.dist-info/RECORD
