Metadata-Version: 2.4
Name: ai-magic-prompt
Version: 0.5.1
Summary: TUI app that enriches prompts using Groq API and project context
Project-URL: Homepage, https://github.com/arterialist/magic-prompt
Project-URL: Repository, https://github.com/arterialist/magic-prompt
Project-URL: Issues, https://github.com/arterialist/magic-prompt/issues
Author: arterialist
License: GPL-3.0-or-later
License-File: LICENSE
Keywords: ai,cli,groq,llm,prompt,prompt-engineering,tui
Classifier: Development Status :: 4 - Beta
Classifier: Environment :: Console
Classifier: Intended Audience :: Developers
Classifier: License :: OSI Approved :: GNU General Public License v3 or later (GPLv3+)
Classifier: Operating System :: OS Independent
Classifier: Programming Language :: Python :: 3
Classifier: Programming Language :: Python :: 3.11
Classifier: Programming Language :: Python :: 3.12
Classifier: Programming Language :: Python :: 3.13
Classifier: Topic :: Software Development :: Libraries :: Python Modules
Classifier: Topic :: Utilities
Requires-Python: >=3.11
Requires-Dist: groq>=0.11.0
Requires-Dist: pathspec>=0.12.0
Requires-Dist: python-dotenv>=1.0.0
Requires-Dist: textual>=0.89.0
